nsEVDx/__init__.py
nsEVDx/_version.py
nsEVDx/evd_model.py
nsEVDx/utils.py
tests/__init__.py
tests/test_evd_model.py
tests/test_utils.py
nsevdx-0.1.1.dist-info/METADATA
nsevdx-0.1.1.dist-info/WHEEL
nsevdx-0.1.1.dist-info/top_level.txt
nsevdx-0.1.1.dist-info/RECORD
