Metadata-Version: 2.4
Name: nsEVDx
Version: 0.1.1
Summary: Modeling Nonstationary Extreme Value Distributions
Home-page: https://github.com/Nischalcs50/nsEVDx
Author: Nischal Kafle
Author-email: Nischal Kafle <nkafle.29@gmail.com>, Claudio Meier <cimeier@memphis.edu>
License: MIT License
Project-URL: Homepage, https://nischalcs50.github.io/nsEVDx/
Project-URL: Repository, https://github.com/Nischalcs50/nsEVDx
Project-URL: Documentation, https://github.com/Nischalcs50/nsEVDx/API_docs
Keywords: Bayesian inference,Frequentist,Generalised extreme value,Generalised pareto,Frequency analyses,Hydroclimatology
Requires-Python: >=3.9
Requires-Dist: numpy
Requires-Dist: scipy
Requires-Dist: matplotlib
Requires-Dist: seaborn
Provides-Extra: dev
Requires-Dist: pytest; extra == "dev"
Dynamic: author
Dynamic: requires-python
